LICENSE
MANIFEST.in
README.md
setup.py
ADSBibTeX.egg-info/PKG-INFO
ADSBibTeX.egg-info/SOURCES.txt
ADSBibTeX.egg-info/dependency_links.txt
ADSBibTeX.egg-info/entry_points.txt
ADSBibTeX.egg-info/not-zip-safe
ADSBibTeX.egg-info/pbr.json
ADSBibTeX.egg-info/requires.txt
ADSBibTeX.egg-info/top_level.txt
adsbibtex/__init__.py
adsbibtex/adsbibtex.py
adsbibtex/adsbibtex_cache.py
adsbibtex/adsbibtex_exceptions.py
adsbibtex/bibcode_to_bibtex.py
adsbibtex/query_ads.py