Metadata-Version: 1.1
Name: ADSBibTeX
Version: 1.0.8
Summary: ADSBibTeX
Home-page: https://github.com/ryanvarley/adsbibtex
Author: Ryan Varley
Author-email: ryan@ryanvarley.uk
License: MIT
Platform: UNKNOWN
Classifier: Development Status :: 4 - Beta
Classifier: Environment :: Console
Classifier: Intended Audience :: Education
Classifier: Intended Audience :: Science/Research
Classifier: License :: OSI Approved :: MIT License
Classifier: Natural Language :: English
Classifier: Operating System :: MacOS
Classifier: Programming Language :: Python :: 2.7
Classifier: Topic :: Scientific/Engineering :: Astronomy
